enlyze/__init__.py
enlyze/_version.py
enlyze/auth.py
enlyze/client.py
enlyze/constants.py
enlyze/errors.py
enlyze/iterable_tools.py
enlyze/models.py
enlyze/py.typed
enlyze/schema.py
enlyze/validators.py
enlyze/api_client/__init__.py
enlyze/api_client/client.py
enlyze/api_client/models.py
enlyze-3.0.1.dist-info/licenses/LICENSE
enlyze-3.0.1.dist-info/METADATA
enlyze-3.0.1.dist-info/WHEEL
enlyze-3.0.1.dist-info/top_level.txt
enlyze-3.0.1.dist-info/RECORD
