Metadata-Version: 2.4
Name: enlyze
Version: 3.0.1
Summary: Python SDK for interacting with the ENLYZE platform https://www.enlyze.com
Author-email: ENLYZE GmbH <hello@enlyze.com>
License: MIT
Classifier: Programming Language :: Python :: 3 :: Only
Classifier: Programming Language :: Python :: 3.10
Classifier: Programming Language :: Python :: 3.11
Classifier: Programming Language :: Python :: 3.12
Classifier: Programming Language :: Python :: 3.13
Requires-Python: >=3.10
License-File: LICENSE
Requires-Dist: httpx
Requires-Dist: pandas>=2
Requires-Dist: pydantic>=2
Provides-Extra: docs
Requires-Dist: sphinx; extra == "docs"
Requires-Dist: sphinx-rtd-theme; extra == "docs"
Requires-Dist: sphinx-tabs; extra == "docs"
Requires-Dist: sphinxcontrib-spelling; extra == "docs"
Provides-Extra: lint
Requires-Dist: bandit; extra == "lint"
Requires-Dist: black; extra == "lint"
Requires-Dist: flake8; extra == "lint"
Requires-Dist: isort; extra == "lint"
Requires-Dist: mypy; extra == "lint"
Requires-Dist: pyproject-fmt; extra == "lint"
Requires-Dist: tox-ini-fmt; extra == "lint"
Provides-Extra: test
Requires-Dist: coverage; extra == "test"
Requires-Dist: hypothesis; extra == "test"
Requires-Dist: pandas-stubs; extra == "test"
Requires-Dist: pytest; extra == "test"
Requires-Dist: pytest-cov; extra == "test"
Requires-Dist: pytest-randomly; extra == "test"
Requires-Dist: pytest-sugar; extra == "test"
Requires-Dist: pytest-xdist; extra == "test"
Requires-Dist: respx; extra == "test"
Dynamic: license-file
